voxit/voxit.py
voxit-0.0.1.dist-info/LICENSE
voxit-0.0.1.dist-info/METADATA
voxit-0.0.1.dist-info/WHEEL
voxit-0.0.1.dist-info/entry_points.txt
voxit-0.0.1.dist-info/top_level.txt
voxit-0.0.1.dist-info/RECORD
