Metadata-Version: 2.1
Name: voxit
Version: 0.0.1
Summary: A simple text to speech & speech to text tool using OpenAI API
Author-email: sean1832 <dev@zekezhang.com>
License: Apache License
Project-URL: Homepage, https://github.com/sean1832/voxit
Project-URL: Issues, https://github.com/sean1832/voxit/issues
Classifier: Development Status :: 1 - Planning
Classifier: Environment :: Console
Requires-Python: >=3.8
License-File: LICENSE
Requires-Dist: openai ==1.53.0
Requires-Dist: pydub >=0.25.1
Requires-Dist: cryptography >=43.0.3
Requires-Dist: halo >=0.0.31
Requires-Dist: tqdm >=4.66.6
